iggyenrich/__init__.py
iggyenrich/iggy_data_package.py
iggyenrich/iggy_enrich.py
iggyenrich-0.0.4.dist-info/LICENSE
iggyenrich-0.0.4.dist-info/METADATA
iggyenrich-0.0.4.dist-info/WHEEL
iggyenrich-0.0.4.dist-info/top_level.txt
iggyenrich-0.0.4.dist-info/RECORD
