Metadata-Version: 2.1
Name: iggyenrich
Version: 0.0.4
Summary: Enrich data using Iggy (askiggy.com)
Home-page: https://github.com/askiggy/iggy-enrich-python
Author: Iggy
Author-email: support@askiggy.com
Project-URL: Issue Tracker, https://github.com/askiggy/iggy-enrich-python/issues
Keywords: iggy askiggy location gis geospatial geography data science machine learning
Classifier: Programming Language :: Python :: 3
Classifier: License :: OSI Approved :: MIT License
Classifier: Operating System :: OS Independent
Requires-Python: >=3.6
License-File: LICENSE
Requires-Dist: fastparquet (==0.7.1)
Requires-Dist: pandas (==1.3.4)
Requires-Dist: geopandas
Requires-Dist: pyarrow (==5.0.0)
Requires-Dist: pydantic (==1.8.2)
Requires-Dist: pyquadkey2 (==0.2.0)
Requires-Dist: Shapely (==1.8.0)
